CEScore/CEScore.py
CEScore/Functions.py
CEScore/SUBTLEX_US_frequency_list.csv
CEScore/__init__.py
CEScore/__main__.py
CEScore/concrete_words.tsv
CEScore-0.0.1.dist-info/LICENSE
CEScore-0.0.1.dist-info/METADATA
CEScore-0.0.1.dist-info/WHEEL
CEScore-0.0.1.dist-info/entry_points.txt
CEScore-0.0.1.dist-info/top_level.txt
CEScore-0.0.1.dist-info/RECORD
